setup.py
src/graf/__init__.py
src/graf/builtins/__init__.py
src/graf/plugins/__init__.py
src/graf/plugins/filters/__init__.py
src/graf/plugins/loaders/__init__.py
src/graf/plugins/parsers/__init__.py
src/graf/plugins/parsers/jasco.py
src/graf_parser_jasco.egg-info/PKG-INFO
src/graf_parser_jasco.egg-info/SOURCES.txt
src/graf_parser_jasco.egg-info/dependency_links.txt
src/graf_parser_jasco.egg-info/entry_points.txt
src/graf_parser_jasco.egg-info/requires.txt
src/graf_parser_jasco.egg-info/top_level.txt
src/graf_parser_jasco.egg-info/zip-safe