Metadata-Version: 1.1
Name: graf-parser-jasco
Version: 0.1.0
Summary: Graf parser plugin for reading JASCO txt file
Home-page: UNKNOWN
Author: Alisue
Author-email: lambdalisue@hashnote.net
License: MIT
Keywords: graf,JASCO,parser
Platform: UNKNOWN
Classifier: Intended Audience :: Developers
Classifier: License :: OSI Approved :: MIT License
Classifier: Programming Language :: Python
